django2_manager_cache/__init__.py
django2_manager_cache/cache_manager.py
django2_manager_cache/mixins.py
django2_manager_cache/models.py
django2_manager_cache/model_cache_sharing/__init__.py
django2_manager_cache/model_cache_sharing/types.py
django2_manager_cache/model_cache_sharing/backends/__init__.py
django2_manager_cache/model_cache_sharing/backends/base.py
django2_manager_cache/model_cache_sharing/backends/ipc.py
django2_manager_cache/model_cache_sharing/backends/shared_memory.py
django2_manager_cache-1.0.1.dist-info/AUTHORS.md
django2_manager_cache-1.0.1.dist-info/LICENSE
django2_manager_cache-1.0.1.dist-info/METADATA
django2_manager_cache-1.0.1.dist-info/WHEEL
django2_manager_cache-1.0.1.dist-info/top_level.txt
django2_manager_cache-1.0.1.dist-info/RECORD
